model_creator/__init__.py
model_creator/auto_encoder.py
model_creator/auto_encoder_tuning.py
model_creator/config_default.py
model_creator/decoupe.py
model_creator/preprocess.py
model_creator/train.py
model_creator/tuner.py
model_creator/use_case_model.py
model_creator_bird_sing_v2-0.2.0.dist-info/LICENCE.txt
model_creator_bird_sing_v2-0.2.0.dist-info/METADATA
model_creator_bird_sing_v2-0.2.0.dist-info/WHEEL
model_creator_bird_sing_v2-0.2.0.dist-info/top_level.txt
model_creator_bird_sing_v2-0.2.0.dist-info/RECORD
