Metadata-Version: 2.1
Name: model-creator-bird-sing-v2
Version: 0.2.0
Summary: Autoencoder singing
Home-page: https://github.com/sonicpierre/Music_VAE_Generation
Author: VIRGAUX Pierre
Author-email: pvirgaux@gmail.com
License: MIT
Platform: UNKNOWN
Classifier: Programming Language :: Python :: 3
Classifier: License :: OSI Approved :: MIT License
Classifier: Operating System :: OS Independent
License-File: LICENCE.txt
Requires-Dist: tensorflow (==2.3.1)
Requires-Dist: mutagen
Requires-Dist: pydub
Requires-Dist: ray
Requires-Dist: librosa
Requires-Dist: keras-tuner
Requires-Dist: wandb
